pyunit_evaluate/__init__.py
pyunit_evaluate/topk/__init__.py
pyunit_evaluate/topk/edges.py
pyunit_evaluate/topk/hits.py
pyunit_evaluate/topk/map.py
pyunit_evaluate/topk/mrr.py
pyunit_evaluate/topk/ndcg.py
pyunit_evaluate/topk/precision.py
pyunit_evaluate/topk/topk.py
pyunit_evaluate-2025.5.26.dist-info/METADATA
pyunit_evaluate-2025.5.26.dist-info/WHEEL
pyunit_evaluate-2025.5.26.dist-info/top_level.txt
pyunit_evaluate-2025.5.26.dist-info/RECORD
