Metadata-Version: 2.4
Name: pyunit-evaluate
Version: 2025.5.26
Summary: 一些关于机器学习的评价指标
Maintainer-email: 张伟 <jtyoui@qq.com>
Project-URL: Repository, https://github.com/pyunits/pyunit_evaluate.git
Keywords: 机器学习,评价指标
Requires-Python: >=3.8
Requires-Dist: numpy
